TimeBaran/TimeBaran.py
TimeBaran/__init__.py
timebaran-0.0.3.dist-info/LICENSE
timebaran-0.0.3.dist-info/METADATA
timebaran-0.0.3.dist-info/WHEEL
timebaran-0.0.3.dist-info/top_level.txt
timebaran-0.0.3.dist-info/RECORD
