Metadata-Version: 2.2
Name: TimeBaran
Version: 0.0.3
Summary: A Python library for managing time and displaying Persian (Jalali) calendar events and daily supplications.
Author-email: Ali Ayati Qaffari <ayatiali910@gmail.com>
License: MIT License
Project-URL: Profile, https://github.com/MrAAQPy
Project-URL: github, https://github.com/MrAAQPy/TimeBaran
Project-URL: issue, https://github.com/MrAAQPy/TimeBaran/issues
Project-URL: bale, https://ble.ir/aaq1386
Requires-Python: >=3.7
License-File: LICENSE
Requires-Dist: lxml
Requires-Dist: pytz
Requires-Dist: jdatetime
Requires-Dist: requests
Requires-Dist: beautifulsoup4
Requires-Dist: tzlocal
Requires-Dist: regex
